{
    "latitude": -22.3193039,
    "longitude": -65.8306389,
    "timezone": "America/La_Paz",
    "currently": {
        "time": 1578932852,
        "summary": "Overcast",
        "icon": "cloudy",
        "precipIntensity": 0.0033,
        "precipProbability": 0.13,
        "precipType": "rain",
        "temperature": 60,
        "apparentTemperature": 60,
        "dewPoint": 43.7,
        "humidity": 0.55,
        "pressure": 1011.1,
        "windSpeed": 5.8,
        "windGust": 6.03,
        "windBearing": 32,
        "cloudCover": 0.99,
        "uvIndex": 7,
        "visibility": 10,
        "ozone": 242.1
    },
    "hourly": {
        "summary": "Possible light rain tonight.",
        "icon": "rain",
        "data": [
            {
                "time": 1578931200,
                "summary": "Overcast",
                "icon": "cloudy",
                "precipIntensity": 0.0035,
                "precipProbability": 0.13,
                "precipType": "rain",
                "temperature": 58.61,
                "apparentTemperature": 58.61,
                "dewPoint": 44.11,
                "humidity": 0.59,
                "pressure": 1011.9,
                "windSpeed": 5.48,
                "windGust": 6.04,
                "windBearing": 32,
                "cloudCover": 1,
                "uvIndex": 7,
                "visibility": 10,
                "ozone": 242.1
            },
            {
                "time": 1578934800,
                "summary": "Overcast",
                "icon": "cloudy",
                "precipIntensity": 0.0028,
                "precipProbability": 0.11,
                "precipType": "rain",
                "temperature": 61.62,
                "apparentTemperature": 61.62,
                "dewPoint": 43.14,
                "humidity": 0.51,
                "pressure": 1010.1,
                "windSpeed": 6.11,
                "windGust": 6.11,
                "windBearing": 31,
                "cloudCover": 0.97,
                "uvIndex": 8,
                "visibility": 10,
                "ozone": 242.1
            },
            {
                "time": 1578938400,
                "summary": "Overcast",
                "icon": "cloudy",
                "precipIntensity": 0.0023,
                "precipProbability": 0.1,
                "precipType": "rain",
                "temperature": 63.82,
                "apparentTemperature": 63.82,
                "dewPoint": 41.8,
                "humidity": 0.45,
                "pressure": 1008.7,
                "windSpeed": 6.59,
                "windGust": 6.59,
                "windBearing": 27,
                "cloudCover": 0.89,
                "uvIndex": 8,
                "visibility": 10,
                "ozone": 241.9
            },
            {
                "time": 1578942000,
                "summary": "Overcast",
                "icon": "cloudy",
                "precipIntensity": 0.0013,
                "precipProbability": 0.09,
                "precipType": "rain",
                "temperature": 64.86,
                "apparentTemperature": 64.86,
                "dewPoint": 40.94,
                "humidity": 0.42,
                "pressure": 1007.4,
                "windSpeed": 7.26,
                "windGust": 7.26,
                "windBearing": 25,
                "cloudCover": 0.89,
                "uvIndex": 7,
                "visibility": 10,
                "ozone": 241.5
            },
            {
                "time": 1578945600,
                "summary": "Overcast",
                "icon": "cloudy",
                "precipIntensity": 0.0013,
                "precipProbability": 0.08,
                "precipType": "rain",
                "temperature": 64.49,
                "apparentTemperature": 64.49,
                "dewPoint": 40.73,
                "humidity": 0.42,
                "pressure": 1006.4,
                "windSpeed": 9.13,
                "windGust": 9.13,
                "windBearing": 32,
                "cloudCover": 0.97,
                "uvIndex": 5,
                "visibility": 10,
                "ozone": 240.8
            },
            {
                "time": 1578949200,
                "summary": "Overcast",
                "icon": "cloudy",
                "precipIntensity": 0.01,
                "precipProbability": 0.1,
                "precipType": "rain",
                "temperature": 62.38,
                "apparentTemperature": 62.38,
                "dewPoint": 41.62,
                "humidity": 0.47,
                "pressure": 1006.8,
                "windSpeed": 10.53,
                "windGust": 10.53,
                "windBearing": 37,
                "cloudCover": 0.99,
                "uvIndex": 3,
                "visibility": 10,
                "ozone": 240.3
            },
            {
                "time": 1578952800,
                "summary": "Overcast",
                "icon": "cloudy",
                "precipIntensity": 0.0089,
                "precipProbability": 0.14,
                "precipType": "rain",
                "temperature": 60.32,
                "apparentTemperature": 60.32,
                "dewPoint": 42.36,
                "humidity": 0.51,
                "pressure": 1007.6,
                "windSpeed": 8.62,
                "windGust": 11.5,
                "windBearing": 31,
                "cloudCover": 0.97,
                "uvIndex": 1,
                "visibility": 10,
                "ozone": 240.2
            },
            {
                "time": 1578956400,
                "summary": "Overcast",
                "icon": "cloudy",
                "precipIntensity": 0.0019,
                "precipProbability": 0.13,
                "precipType": "rain",
                "temperature": 57.65,
                "apparentTemperature": 57.65,
                "dewPoint": 43.54,
                "humidity": 0.59,
                "pressure": 1009,
                "windSpeed": 9.07,
                "windGust": 15.94,
                "windBearing": 27,
                "cloudCover": 0.95,
                "uvIndex": 0,
                "visibility": 10,
                "ozone": 240.3
            },
            {
                "time": 1578960000,
                "summary": "Overcast",
                "icon": "cloudy",
                "precipIntensity": 0.0047,
                "precipProbability": 0.16,
                "precipType": "rain",
                "temperature": 54.89,
                "apparentTemperature": 54.89,
                "dewPoint": 43.75,
                "humidity": 0.66,
                "pressure": 1010.3,
                "windSpeed": 8.13,
                "windGust": 18.95,
                "windBearing": 35,
                "cloudCover": 0.94,
                "uvIndex": 0,
                "visibility": 10,
                "ozone": 240.4
            },
            {
                "time": 1578963600,
                "summary": "Overcast",
                "icon": "cloudy",
                "precipIntensity": 0.0129,
                "precipProbability": 0.22,
                "precipType": "rain",
                "temperature": 53.19,
                "apparentTemperature": 53.19,
                "dewPoint": 43.09,
                "humidity": 0.68,
                "pressure": 1011.8,
                "windSpeed": 6.54,
                "windGust": 19.37,
                "windBearing": 47,
                "cloudCover": 0.95,
                "uvIndex": 0,
                "visibility": 10,
                "ozone": 240.6
            },
            {
                "time": 1578967200,
                "summary": "Possible Light Rain",
                "icon": "rain",
                "precipIntensity": 0.0395,
                "precipProbability": 0.26,
                "precipType": "rain",
                "temperature": 51.68,
                "apparentTemperature": 51.68,
                "dewPoint": 41.66,
                "humidity": 0.69,
                "pressure": 1013.1,
                "windSpeed": 6.14,
                "windGust": 18.38,
                "windBearing": 36,
                "cloudCover": 0.98,
                "uvIndex": 0,
                "visibility": 10,
                "ozone": 240.9
            },
            {
                "time": 1578970800,
                "summary": "Overcast",
                "icon": "cloudy",
                "precipIntensity": 0.025,
                "precipProbability": 0.24,
                "precipType": "rain",
                "temperature": 50.52,
                "apparentTemperature": 50.52,
                "dewPoint": 41.13,
                "humidity": 0.7,
                "pressure": 1013.9,
                "windSpeed": 6.29,
                "windGust": 17.16,
                "windBearing": 34,
                "cloudCover": 0.99,
                "uvIndex": 0,
                "visibility": 10,
                "ozone": 241.2
            },
            {
                "time": 1578974400,
                "summary": "Overcast",
                "icon": "cloudy",
                "precipIntensity": 0.0094,
                "precipProbability": 0.21,
                "precipType": "rain",
                "temperature": 49.82,
                "apparentTemperature": 47.77,
                "dewPoint": 41.36,
                "humidity": 0.73,
                "pressure": 1014,
                "windSpeed": 5.4,
                "windGust": 16.11,
                "windBearing": 43,
                "cloudCover": 1,
                "uvIndex": 0,
                "visibility": 10,
                "ozone": 241.2
            },
            {
                "time": 1578978000,
                "summary": "Overcast",
                "icon": "cloudy",
                "precipIntensity": 0.0149,
                "precipProbability": 0.24,
                "precipType": "rain",
                "temperature": 49.15,
                "apparentTemperature": 46.95,
                "dewPoint": 41.89,
                "humidity": 0.76,
                "pressure": 1013.7,
                "windSpeed": 5.47,
                "windGust": 14.83,
                "windBearing": 56,
                "cloudCover": 1,
                "uvIndex": 0,
                "visibility": 10,
                "ozone": 241.2
            },
            {
                "time": 1578981600,
                "summary": "Overcast",
                "icon": "cloudy",
                "precipIntensity": 0.0194,
                "precipProbability": 0.23,
                "precipType": "rain",
                "temperature": 48.81,
                "apparentTemperature": 47.2,
                "dewPoint": 42.48,
                "humidity": 0.79,
                "pressure": 1013.3,
                "windSpeed": 4.41,
                "windGust": 13.31,
                "windBearing": 42,
                "cloudCover": 0.99,
                "uvIndex": 0,
                "visibility": 10,
                "ozone": 241.6
            },
            {
                "time": 1578985200,
                "summary": "Overcast",
                "icon": "cloudy",
                "precipIntensity": 0.0162,
                "precipProbability": 0.21,
                "precipType": "rain",
                "temperature": 48.33,
                "apparentTemperature": 47.34,
                "dewPoint": 42.84,
                "humidity": 0.81,
                "pressure": 1013,
                "windSpeed": 3.5,
                "windGust": 11.26,
                "windBearing": 49,
                "cloudCover": 0.97,
                "uvIndex": 0,
                "visibility": 10,
                "ozone": 242.4
            },
            {
                "time": 1578988800,
                "summary": "Overcast",
                "icon": "cloudy",
                "precipIntensity": 0.0109,
                "precipProbability": 0.2,
                "precipType": "rain",
                "temperature": 47.96,
                "apparentTemperature": 47.1,
                "dewPoint": 43.1,
                "humidity": 0.83,
                "pressure": 1013.1,
                "windSpeed": 3.29,
                "windGust": 8.98,
                "windBearing": 63,
                "cloudCover": 0.95,
                "uvIndex": 0,
                "visibility": 10,
                "ozone": 243.3
            },
            {
                "time": 1578992400,
                "summary": "Overcast",
                "icon": "cloudy",
                "precipIntensity": 0.0056,
                "precipProbability": 0.19,
                "precipType": "rain",
                "temperature": 47.94,
                "apparentTemperature": 47.94,
                "dewPoint": 43.45,
                "humidity": 0.84,
                "pressure": 1013.4,
                "windSpeed": 2.78,
                "windGust": 7.55,
                "windBearing": 20,
                "cloudCover": 0.92,
                "uvIndex": 0,
                "visibility": 10,
                "ozone": 244.4
            },
            {
                "time": 1578996000,
                "summary": "Overcast",
                "icon": "cloudy",
                "precipIntensity": 0.002,
                "precipProbability": 0.17,
                "precipType": "rain",
                "temperature": 48.39,
                "apparentTemperature": 47.67,
                "dewPoint": 44,
                "humidity": 0.85,
                "pressure": 1013.7,
                "windSpeed": 3.2,
                "windGust": 7.48,
                "windBearing": 357,
                "cloudCover": 0.91,
                "uvIndex": 0,
                "visibility": 10,
                "ozone": 245.2
            },
            {
                "time": 1578999600,
                "summary": "Mostly Cloudy",
                "icon": "partly-cloudy-day",
                "precipIntensity": 0.0006,
                "precipProbability": 0.15,
                "precipType": "rain",
                "temperature": 49.29,
                "apparentTemperature": 48.17,
                "dewPoint": 44.17,
                "humidity": 0.82,
                "pressure": 1014,
                "windSpeed": 3.84,
                "windGust": 8.26,
                "windBearing": 359,
                "cloudCover": 0.85,
                "uvIndex": 1,
                "visibility": 10,
                "ozone": 246.2
            },
            {
                "time": 1579003200,
                "summary": "Mostly Cloudy",
                "icon": "partly-cloudy-day",
                "precipIntensity": 0.0003,
                "precipProbability": 0.07,
                "precipType": "rain",
                "temperature": 51.19,
                "apparentTemperature": 51.19,
                "dewPoint": 44.58,
                "humidity": 0.78,
                "pressure": 1013.9,
                "windSpeed": 4.33,
                "windGust": 9.41,
                "windBearing": 31,
                "cloudCover": 0.82,
                "uvIndex": 2,
                "visibility": 10,
                "ozone": 246.9
            },
            {
                "time": 1579006800,
                "summary": "Mostly Cloudy",
                "icon": "partly-cloudy-day",
                "precipIntensity": 0,
                "precipProbability": 0,
                "temperature": 54.24,
                "apparentTemperature": 54.24,
                "dewPoint": 45.34,
                "humidity": 0.72,
                "pressure": 1013.2,
                "windSpeed": 5.46,
                "windGust": 10.94,
                "windBearing": 54,
                "cloudCover": 0.72,
                "uvIndex": 5,
                "visibility": 10,
                "ozone": 247.7
            },
            {
                "time": 1579010400,
                "summary": "Mostly Cloudy",
                "icon": "partly-cloudy-day",
                "precipIntensity": 0,
                "precipProbability": 0,
                "temperature": 57.16,
                "apparentTemperature": 57.16,
                "dewPoint": 44.91,
                "humidity": 0.64,
                "pressure": 1012,
                "windSpeed": 7.01,
                "windGust": 12.82,
                "windBearing": 39,
                "cloudCover": 0.76,
                "uvIndex": 7,
                "visibility": 10,
                "ozone": 248.4
            },
            {
                "time": 1579014000,
                "summary": "Mostly Cloudy",
                "icon": "partly-cloudy-day",
                "precipIntensity": 0,
                "precipProbability": 0,
                "temperature": 60.36,
                "apparentTemperature": 60.36,
                "dewPoint": 44.43,
                "humidity": 0.56,
                "pressure": 1010.6,
                "windSpeed": 8.54,
                "windGust": 14.59,
                "windBearing": 25,
                "cloudCover": 0.72,
                "uvIndex": 9,
                "visibility": 10,
                "ozone": 248.7
            },
            {
                "time": 1579017600,
                "summary": "Partly Cloudy",
                "icon": "partly-cloudy-day",
                "precipIntensity": 0.0007,
                "precipProbability": 0.03,
                "precipType": "rain",
                "temperature": 63.23,
                "apparentTemperature": 63.23,
                "dewPoint": 44.25,
                "humidity": 0.5,
                "pressure": 1008.8,
                "windSpeed": 10.1,
                "windGust": 15.98,
                "windBearing": 18,
                "cloudCover": 0.59,
                "uvIndex": 11,
                "visibility": 10,
                "ozone": 248.2
            },
            {
                "time": 1579021200,
                "summary": "Partly Cloudy",
                "icon": "partly-cloudy-day",
                "precipIntensity": 0.0013,
                "precipProbability": 0.05,
                "precipType": "rain",
                "temperature": 66.25,
                "apparentTemperature": 66.25,
                "dewPoint": 42.41,
                "humidity": 0.42,
                "pressure": 1006.9,
                "windSpeed": 11.61,
                "windGust": 17.25,
                "windBearing": 17,
                "cloudCover": 0.51,
                "uvIndex": 12,
                "visibility": 10,
                "ozone": 247.3
            },
            {
                "time": 1579024800,
                "summary": "Mostly Cloudy",
                "icon": "partly-cloudy-day",
                "precipIntensity": 0.0017,
                "precipProbability": 0.05,
                "precipType": "rain",
                "temperature": 68.12,
                "apparentTemperature": 68.12,
                "dewPoint": 40.84,
                "humidity": 0.37,
                "pressure": 1005.5,
                "windSpeed": 13.06,
                "windGust": 18.63,
                "windBearing": 18,
                "cloudCover": 0.62,
                "uvIndex": 10,
                "visibility": 10,
                "ozone": 246.4
            },
            {
                "time": 1579028400,
                "summary": "Partly Cloudy",
                "icon": "partly-cloudy-day",
                "precipIntensity": 0.0017,
                "precipProbability": 0.04,
                "precipType": "rain",
                "temperature": 68.87,
                "apparentTemperature": 68.87,
                "dewPoint": 40.13,
                "humidity": 0.35,
                "pressure": 1004.1,
                "windSpeed": 14.38,
                "windGust": 20.43,
                "windBearing": 19,
                "cloudCover": 0.49,
                "uvIndex": 9,
                "visibility": 10,
                "ozone": 245.6
            },
            {
                "time": 1579032000,
                "summary": "Partly Cloudy",
                "icon": "partly-cloudy-day",
                "precipIntensity": 0.0018,
                "precipProbability": 0.05,
                "precipType": "rain",
                "temperature": 67.87,
                "apparentTemperature": 67.87,
                "dewPoint": 40.22,
                "humidity": 0.36,
                "pressure": 1003.3,
                "windSpeed": 15.9,
                "windGust": 22.3,
                "windBearing": 24,
                "cloudCover": 0.55,
                "uvIndex": 6,
                "visibility": 10,
                "ozone": 245.1
            },
            {
                "time": 1579035600,
                "summary": "Overcast",
                "icon": "cloudy",
                "precipIntensity": 0.0015,
                "precipProbability": 0.04,
                "precipType": "rain",
                "temperature": 65.98,
                "apparentTemperature": 65.98,
                "dewPoint": 41.41,
                "humidity": 0.41,
                "pressure": 1003.2,
                "windSpeed": 16.92,
                "windGust": 23.65,
                "windBearing": 32,
                "cloudCover": 0.9,
                "uvIndex": 3,
                "visibility": 10,
                "ozone": 244.6
            },
            {
                "time": 1579039200,
                "summary": "Overcast",
                "icon": "cloudy",
                "precipIntensity": 0.0041,
                "precipProbability": 0.11,
                "precipType": "rain",
                "temperature": 62.92,
                "apparentTemperature": 62.92,
                "dewPoint": 43.24,
                "humidity": 0.49,
                "pressure": 1004.4,
                "windSpeed": 15.41,
                "windGust": 24.49,
                "windBearing": 37,
                "cloudCover": 0.93,
                "uvIndex": 1,
                "visibility": 10,
                "ozone": 244.4
            },
            {
                "time": 1579042800,
                "summary": "Overcast",
                "icon": "cloudy",
                "precipIntensity": 0.0074,
                "precipProbability": 0.13,
                "precipType": "rain",
                "temperature": 59.23,
                "apparentTemperature": 59.23,
                "dewPoint": 42.98,
                "humidity": 0.55,
                "pressure": 1006.1,
                "windSpeed": 13.21,
                "windGust": 24.78,
                "windBearing": 28,
                "cloudCover": 0.9,
                "uvIndex": 0,
                "visibility": 10,
                "ozone": 244.3
            },
            {
                "time": 1579046400,
                "summary": "Overcast",
                "icon": "cloudy",
                "precipIntensity": 0.0097,
                "precipProbability": 0.16,
                "precipType": "rain",
                "temperature": 55.78,
                "apparentTemperature": 55.78,
                "dewPoint": 43.15,
                "humidity": 0.62,
                "pressure": 1008.1,
                "windSpeed": 11.29,
                "windGust": 23.78,
                "windBearing": 21,
                "cloudCover": 0.88,
                "uvIndex": 0,
                "visibility": 10,
                "ozone": 244.3
            },
            {
                "time": 1579050000,
                "summary": "Overcast",
                "icon": "cloudy",
                "precipIntensity": 0.0083,
                "precipProbability": 0.16,
                "precipType": "rain",
                "temperature": 53.61,
                "apparentTemperature": 53.61,
                "dewPoint": 43.03,
                "humidity": 0.67,
                "pressure": 1009.6,
                "windSpeed": 9.42,
                "windGust": 20.49,
                "windBearing": 38,
                "cloudCover": 0.88,
                "uvIndex": 0,
                "visibility": 10,
                "ozone": 244.4
            },
            {
                "time": 1579053600,
                "summary": "Mostly Cloudy",
                "icon": "partly-cloudy-night",
                "precipIntensity": 0.0063,
                "precipProbability": 0.16,
                "precipType": "rain",
                "temperature": 51.94,
                "apparentTemperature": 51.94,
                "dewPoint": 42.25,
                "humidity": 0.69,
                "pressure": 1011,
                "windSpeed": 8.07,
                "windGust": 15.9,
                "windBearing": 46,
                "cloudCover": 0.8,
                "uvIndex": 0,
                "visibility": 10,
                "ozone": 244.6
            },
            {
                "time": 1579057200,
                "summary": "Overcast",
                "icon": "cloudy",
                "precipIntensity": 0.0189,
                "precipProbability": 0.21,
                "precipType": "rain",
                "temperature": 50.92,
                "apparentTemperature": 50.92,
                "dewPoint": 42.33,
                "humidity": 0.72,
                "pressure": 1011.9,
                "windSpeed": 5.95,
                "windGust": 12.25,
                "windBearing": 44,
                "cloudCover": 0.91,
                "uvIndex": 0,
                "visibility": 10,
                "ozone": 244.9
            },
            {
                "time": 1579060800,
                "summary": "Overcast",
                "icon": "cloudy",
                "precipIntensity": 0.0289,
                "precipProbability": 0.23,
                "precipType": "rain",
                "temperature": 50.26,
                "apparentTemperature": 50.26,
                "dewPoint": 42.47,
                "humidity": 0.75,
                "pressure": 1012.2,
                "windSpeed": 4.32,
                "windGust": 10.28,
                "windBearing": 113,
                "cloudCover": 0.92,
                "uvIndex": 0,
                "visibility": 10,
                "ozone": 245.4
            },
            {
                "time": 1579064400,
                "summary": "Overcast",
                "icon": "cloudy",
                "precipIntensity": 0.025,
                "precipProbability": 0.24,
                "precipType": "rain",
                "temperature": 49.89,
                "apparentTemperature": 47.97,
                "dewPoint": 42.66,
                "humidity": 0.76,
                "pressure": 1012.3,
                "windSpeed": 5.19,
                "windGust": 9.25,
                "windBearing": 154,
                "cloudCover": 0.94,
                "uvIndex": 0,
                "visibility": 10,
                "ozone": 245.9
            },
            {
                "time": 1579068000,
                "summary": "Possible Light Rain",
                "icon": "rain",
                "precipIntensity": 0.0234,
                "precipProbability": 0.26,
                "precipType": "rain",
                "temperature": 49.41,
                "apparentTemperature": 47.49,
                "dewPoint": 42.85,
                "humidity": 0.78,
                "pressure": 1012,
                "windSpeed": 5.06,
                "windGust": 9.13,
                "windBearing": 167,
                "cloudCover": 0.95,
                "uvIndex": 0,
                "visibility": 10,
                "ozone": 246.3
            },
            {
                "time": 1579071600,
                "summary": "Overcast",
                "icon": "cloudy",
                "precipIntensity": 0.0108,
                "precipProbability": 0.21,
                "precipType": "rain",
                "temperature": 48.86,
                "apparentTemperature": 47.76,
                "dewPoint": 42.99,
                "humidity": 0.8,
                "pressure": 1011.8,
                "windSpeed": 3.72,
                "windGust": 10.43,
                "windBearing": 183,
                "cloudCover": 0.97,
                "uvIndex": 0,
                "visibility": 10,
                "ozone": 246.3
            },
            {
                "time": 1579075200,
                "summary": "Overcast",
                "icon": "cloudy",
                "precipIntensity": 0.0066,
                "precipProbability": 0.2,
                "precipType": "rain",
                "temperature": 48.26,
                "apparentTemperature": 46.62,
                "dewPoint": 43.1,
                "humidity": 0.82,
                "pressure": 1012,
                "windSpeed": 4.33,
                "windGust": 12.62,
                "windBearing": 248,
                "cloudCover": 0.99,
                "uvIndex": 0,
                "visibility": 10,
                "ozone": 246.2
            },
            {
                "time": 1579078800,
                "summary": "Overcast",
                "icon": "cloudy",
                "precipIntensity": 0.0043,
                "precipProbability": 0.19,
                "precipType": "rain",
                "temperature": 47.99,
                "apparentTemperature": 46.11,
                "dewPoint": 43.25,
                "humidity": 0.84,
                "pressure": 1012.2,
                "windSpeed": 4.62,
                "windGust": 13.93,
                "windBearing": 258,
                "cloudCover": 0.89,
                "uvIndex": 0,
                "visibility": 10,
                "ozone": 246.4
            },
            {
                "time": 1579082400,
                "summary": "Overcast",
                "icon": "cloudy",
                "precipIntensity": 0.0033,
                "precipProbability": 0.19,
                "precipType": "rain",
                "temperature": 48.01,
                "apparentTemperature": 46.34,
                "dewPoint": 43.53,
                "humidity": 0.84,
                "pressure": 1012.6,
                "windSpeed": 4.31,
                "windGust": 13.69,
                "windBearing": 277,
                "cloudCover": 0.9,
                "uvIndex": 0,
                "visibility": 10,
                "ozone": 247.1
            },
            {
                "time": 1579086000,
                "summary": "Mostly Cloudy",
                "icon": "partly-cloudy-day",
                "precipIntensity": 0.0027,
                "precipProbability": 0.18,
                "precipType": "rain",
                "temperature": 48.9,
                "apparentTemperature": 47.13,
                "dewPoint": 43.44,
                "humidity": 0.81,
                "pressure": 1013.1,
                "windSpeed": 4.69,
                "windGust": 12.56,
                "windBearing": 207,
                "cloudCover": 0.71,
                "uvIndex": 1,
                "visibility": 10,
                "ozone": 248.1
            },
            {
                "time": 1579089600,
                "summary": "Partly Cloudy",
                "icon": "partly-cloudy-day",
                "precipIntensity": 0.002,
                "precipProbability": 0.16,
                "precipType": "rain",
                "temperature": 51.11,
                "apparentTemperature": 51.11,
                "dewPoint": 43.85,
                "humidity": 0.76,
                "pressure": 1013.3,
                "windSpeed": 4.39,
                "windGust": 10.92,
                "windBearing": 176,
                "cloudCover": 0.54,
                "uvIndex": 3,
                "visibility": 10,
                "ozone": 248.8
            },
            {
                "time": 1579093200,
                "summary": "Partly Cloudy",
                "icon": "partly-cloudy-day",
                "precipIntensity": 0.0009,
                "precipProbability": 0.1,
                "precipType": "rain",
                "temperature": 54.39,
                "apparentTemperature": 54.39,
                "dewPoint": 44.53,
                "humidity": 0.69,
                "pressure": 1012.5,
                "windSpeed": 3.59,
                "windGust": 8.17,
                "windBearing": 106,
                "cloudCover": 0.49,
                "uvIndex": 5,
                "visibility": 10,
                "ozone": 249.2
            },
            {
                "time": 1579096800,
                "summary": "Partly Cloudy",
                "icon": "partly-cloudy-day",
                "precipIntensity": 0,
                "precipProbability": 0,
                "temperature": 57.65,
                "apparentTemperature": 57.65,
                "dewPoint": 44.15,
                "humidity": 0.61,
                "pressure": 1011.3,
                "windSpeed": 2.97,
                "windGust": 4.91,
                "windBearing": 58,
                "cloudCover": 0.59,
                "uvIndex": 8,
                "visibility": 10,
                "ozone": 249.1
            },
            {
                "time": 1579100400,
                "summary": "Mostly Cloudy",
                "icon": "partly-cloudy-day",
                "precipIntensity": 0,
                "precipProbability": 0,
                "temperature": 61.09,
                "apparentTemperature": 61.09,
                "dewPoint": 44.24,
                "humidity": 0.54,
                "pressure": 1009.7,
                "windSpeed": 3.3,
                "windGust": 3.32,
                "windBearing": 42,
                "cloudCover": 0.82,
                "uvIndex": 8,
                "visibility": 10,
                "ozone": 248.9
            },
            {
                "time": 1579104000,
                "summary": "Partly Cloudy",
                "icon": "partly-cloudy-day",
                "precipIntensity": 0,
                "precipProbability": 0,
                "temperature": 64.83,
                "apparentTemperature": 64.83,
                "dewPoint": 42.47,
                "humidity": 0.44,
                "pressure": 1008.6,
                "windSpeed": 4.12,
                "windGust": 4.2,
                "windBearing": 28,
                "cloudCover": 0.58,
                "uvIndex": 12,
                "visibility": 10,
                "ozone": 248.6
            }
        ]
    },
    "daily": {
        "summary": "Rain throughout the week.",
        "icon": "rain",
        "data": [
            {
                "time": 1578888000,
                "summary": "Possible light rain in the morning and overnight.",
                "icon": "rain",
                "sunriseTime": 1578909120,
                "sunsetTime": 1578957240,
                "moonPhase": 0.62,
                "precipIntensity": 0.0107,
                "precipIntensityMax": 0.0736,
                "precipIntensityMaxTime": 1578888000,
                "precipProbability": 0.7,
                "precipType": "rain",
                "temperatureHigh": 65.41,
                "temperatureHighTime": 1578942960,
                "temperatureLow": 47.41,
                "temperatureLowTime": 1578990900,
                "apparentTemperatureHigh": 64.91,
                "apparentTemperatureHighTime": 1578942960,
                "apparentTemperatureLow": 46.93,
                "apparentTemperatureLowTime": 1578978480,
                "dewPoint": 42.23,
                "humidity": 0.66,
                "pressure": 1012.5,
                "windSpeed": 5.74,
                "windGust": 19.43,
                "windGustTime": 1578962400,
                "windBearing": 36,
                "cloudCover": 0.98,
                "uvIndex": 8,
                "uvIndexTime": 1578937920,
                "visibility": 10,
                "ozone": 243.4,
                "temperatureMin": 46.84,
                "temperatureMinTime": 1578888000,
                "temperatureMax": 65.41,
                "temperatureMaxTime": 1578942960,
                "apparentTemperatureMin": 43.68,
                "apparentTemperatureMinTime": 1578888000,
                "apparentTemperatureMax": 64.91,
                "apparentTemperatureMaxTime": 1578942960
            },
            {
                "time": 1578974400,
                "summary": "Mostly cloudy throughout the day.",
                "icon": "rain",
                "sunriseTime": 1578995580,
                "sunsetTime": 1579043640,
                "moonPhase": 0.66,
                "precipIntensity": 0.0063,
                "precipIntensityMax": 0.0289,
                "precipIntensityMaxTime": 1579060800,
                "precipProbability": 0.56,
                "precipType": "rain",
                "temperatureHigh": 69.37,
                "temperatureHighTime": 1579028220,
                "temperatureLow": 47.43,
                "temperatureLowTime": 1579080960,
                "apparentTemperatureHigh": 68.87,
                "apparentTemperatureHighTime": 1579028220,
                "apparentTemperatureLow": 46.1,
                "apparentTemperatureLowTime": 1579079400,
                "dewPoint": 42.89,
                "humidity": 0.64,
                "pressure": 1010,
                "windSpeed": 8.42,
                "windGust": 24.81,
                "windGustTime": 1579042080,
                "windBearing": 30,
                "cloudCover": 0.81,
                "uvIndex": 12,
                "uvIndexTime": 1579020720,
                "visibility": 10,
                "ozone": 245.1,
                "temperatureMin": 47.41,
                "temperatureMinTime": 1578990900,
                "temperatureMax": 69.37,
                "temperatureMaxTime": 1579028220,
                "apparentTemperatureMin": 46.93,
                "apparentTemperatureMinTime": 1578978480,
                "apparentTemperatureMax": 68.87,
                "apparentTemperatureMaxTime": 1579028220
            },
            {
                "time": 1579060800,
                "summary": "Mostly cloudy throughout the day.",
                "icon": "rain",
                "sunriseTime": 1579081980,
                "sunsetTime": 1579130040,
                "moonPhase": 0.69,
                "precipIntensity": 0.0069,
                "precipIntensityMax": 0.0291,
                "precipIntensityMaxTime": 1579061220,
                "precipProbability": 0.6,
                "precipType": "rain",
                "temperatureHigh": 70.64,
                "temperatureHighTime": 1579112520,
                "temperatureLow": 48.97,
                "temperatureLowTime": 1579171320,
                "apparentTemperatureHigh": 70.14,
                "apparentTemperatureHighTime": 1579112520,
                "apparentTemperatureLow": 48.38,
                "apparentTemperatureLowTime": 1579171380,
                "dewPoint": 42.45,
                "humidity": 0.62,
                "pressure": 1009.8,
                "windSpeed": 6.54,
                "windGust": 18.65,
                "windGustTime": 1579130460,
                "windBearing": 24,
                "cloudCover": 0.87,
                "uvIndex": 12,
                "uvIndexTime": 1579104240,
                "visibility": 9.768,
                "ozone": 246.3,
                "temperatureMin": 47.43,
                "temperatureMinTime": 1579080960,
                "temperatureMax": 70.64,
                "temperatureMaxTime": 1579112520,
                "apparentTemperatureMin": 46.1,
                "apparentTemperatureMinTime": 1579079400,
                "apparentTemperatureMax": 70.14,
                "apparentTemperatureMaxTime": 1579112520
            },
            {
                "time": 1579147200,
                "summary": "Possible light rain in the morning and overnight.",
                "icon": "rain",
                "sunriseTime": 1579168440,
                "sunsetTime": 1579216440,
                "moonPhase": 0.73,
                "precipIntensity": 0.0176,
                "precipIntensityMax": 0.065,
                "precipIntensityMaxTime": 1579178400,
                "precipProbability": 0.68,
                "precipType": "rain",
                "temperatureHigh": 63.84,
                "temperatureHighTime": 1579200120,
                "temperatureLow": 47.85,
                "temperatureLowTime": 1579249860,
                "apparentTemperatureHigh": 63.34,
                "apparentTemperatureHighTime": 1579200120,
                "apparentTemperatureLow": 45.54,
                "apparentTemperatureLowTime": 1579252140,
                "dewPoint": 43.46,
                "humidity": 0.68,
                "pressure": 1013.6,
                "windSpeed": 6.81,
                "windGust": 14.76,
                "windGustTime": 1579209540,
                "windBearing": 51,
                "cloudCover": 1,
                "uvIndex": 7,
                "uvIndexTime": 1579192560,
                "visibility": 9.72,
                "ozone": 246.4,
                "temperatureMin": 48.97,
                "temperatureMinTime": 1579171320,
                "temperatureMax": 63.84,
                "temperatureMaxTime": 1579200120,
                "apparentTemperatureMin": 47.33,
                "apparentTemperatureMinTime": 1579233600,
                "apparentTemperatureMax": 63.34,
                "apparentTemperatureMaxTime": 1579200120
            },
            {
                "time": 1579233600,
                "summary": "Possible light rain in the morning and overnight.",
                "icon": "rain",
                "sunriseTime": 1579254900,
                "sunsetTime": 1579302840,
                "moonPhase": 0.77,
                "precipIntensity": 0.0197,
                "precipIntensityMax": 0.0644,
                "precipIntensityMaxTime": 1579316760,
                "precipProbability": 0.65,
                "precipType": "rain",
                "temperatureHigh": 64.22,
                "temperatureHighTime": 1579290120,
                "temperatureLow": 47.47,
                "temperatureLowTime": 1579336680,
                "apparentTemperatureHigh": 63.72,
                "apparentTemperatureHighTime": 1579290120,
                "apparentTemperatureLow": 44.78,
                "apparentTemperatureLowTime": 1579318080,
                "dewPoint": 43.79,
                "humidity": 0.69,
                "pressure": 1013.4,
                "windSpeed": 9.6,
                "windGust": 20.23,
                "windGustTime": 1579316700,
                "windBearing": 14,
                "cloudCover": 0.94,
                "uvIndex": 7,
                "uvIndexTime": 1579279020,
                "visibility": 9.527,
                "ozone": 245.4,
                "temperatureMin": 47.85,
                "temperatureMinTime": 1579249860,
                "temperatureMax": 64.22,
                "temperatureMaxTime": 1579290120,
                "apparentTemperatureMin": 44.78,
                "apparentTemperatureMinTime": 1579318080,
                "apparentTemperatureMax": 63.72,
                "apparentTemperatureMaxTime": 1579290120
            },
            {
                "time": 1579320000,
                "summary": "Rain in the evening and overnight.",
                "icon": "rain",
                "sunriseTime": 1579341300,
                "sunsetTime": 1579389240,
                "moonPhase": 0.8,
                "precipIntensity": 0.0327,
                "precipIntensityMax": 0.1538,
                "precipIntensityMaxTime": 1579402740,
                "precipProbability": 0.67,
                "precipType": "rain",
                "temperatureHigh": 65.27,
                "temperatureHighTime": 1579369680,
                "temperatureLow": 48.1,
                "temperatureLowTime": 1579424160,
                "apparentTemperatureHigh": 64.77,
                "apparentTemperatureHighTime": 1579369680,
                "apparentTemperatureLow": 46.61,
                "apparentTemperatureLowTime": 1579424940,
                "dewPoint": 43.58,
                "humidity": 0.68,
                "pressure": 1011.2,
                "windSpeed": 5.64,
                "windGust": 19.86,
                "windGustTime": 1579320000,
                "windBearing": 62,
                "cloudCover": 0.96,
                "uvIndex": 8,
                "uvIndexTime": 1579367820,
                "visibility": 9.326,
                "ozone": 240.4,
                "temperatureMin": 47.47,
                "temperatureMinTime": 1579336680,
                "temperatureMax": 65.27,
                "temperatureMaxTime": 1579369680,
                "apparentTemperatureMin": 44.94,
                "apparentTemperatureMinTime": 1579320000,
                "apparentTemperatureMax": 64.77,
                "apparentTemperatureMaxTime": 1579369680
            },
            {
                "time": 1579406400,
                "summary": "Possible drizzle in the morning.",
                "icon": "rain",
                "sunriseTime": 1579427760,
                "sunsetTime": 1579475640,
                "moonPhase": 0.84,
                "precipIntensity": 0.0091,
                "precipIntensityMax": 0.1121,
                "precipIntensityMaxTime": 1579406400,
                "precipProbability": 0.74,
                "precipType": "rain",
                "temperatureHigh": 62.43,
                "temperatureHighTime": 1579462860,
                "temperatureLow": 47.8,
                "temperatureLowTime": 1579501440,
                "apparentTemperatureHigh": 61.93,
                "apparentTemperatureHighTime": 1579462860,
                "apparentTemperatureLow": 47.35,
                "apparentTemperatureLowTime": 1579494360,
                "dewPoint": 43.61,
                "humidity": 0.7,
                "pressure": 1011.2,
                "windSpeed": 7.06,
                "windGust": 19.41,
                "windGustTime": 1579479300,
                "windBearing": 15,
                "cloudCover": 0.92,
                "uvIndex": 8,
                "uvIndexTime": 1579455420,
                "visibility": 10,
                "ozone": 239.2,
                "temperatureMin": 48.1,
                "temperatureMinTime": 1579424160,
                "temperatureMax": 62.43,
                "temperatureMaxTime": 1579462860,
                "apparentTemperatureMin": 46.61,
                "apparentTemperatureMinTime": 1579424940,
                "apparentTemperatureMax": 61.93,
                "apparentTemperatureMaxTime": 1579462860
            },
            {
                "time": 1579492800,
                "summary": "Possible light rain in the evening and overnight.",
                "icon": "rain",
                "sunriseTime": 1579514220,
                "sunsetTime": 1579562040,
                "moonPhase": 0.87,
                "precipIntensity": 0.0219,
                "precipIntensityMax": 0.0845,
                "precipIntensityMaxTime": 1579575240,
                "precipProbability": 0.58,
                "precipType": "rain",
                "temperatureHigh": 62.41,
                "temperatureHighTime": 1579548420,
                "temperatureLow": 48.77,
                "temperatureLowTime": 1579604220,
                "apparentTemperatureHigh": 61.91,
                "apparentTemperatureHighTime": 1579548420,
                "apparentTemperatureLow": 48.18,
                "apparentTemperatureLowTime": 1579604340,
                "dewPoint": 44.38,
                "humidity": 0.71,
                "pressure": 1008.7,
                "windSpeed": 4.54,
                "windGust": 14.68,
                "windGustTime": 1579554060,
                "windBearing": 62,
                "cloudCover": 0.96,
                "uvIndex": 8,
                "uvIndexTime": 1579540320,
                "visibility": 8.959,
                "ozone": 237.9,
                "temperatureMin": 47.8,
                "temperatureMinTime": 1579501440,
                "temperatureMax": 62.41,
                "temperatureMaxTime": 1579548420,
                "apparentTemperatureMin": 47.35,
                "apparentTemperatureMinTime": 1579494360,
                "apparentTemperatureMax": 61.91,
                "apparentTemperatureMaxTime": 1579548420
            }
        ]
    },
    "offset": -4
}
